[{"ForegroundId":"SpecialNode","Position":{"X":0,"Y":2}},{"ForegroundId":"SpecialNode","Position":{"X":0,"Y":3}},{"ForegroundId":"SpecialNode","Position":{"X":0,"Y":4}},{"ForegroundId":"SpecialNode","Position":{"X":0,"Y":5}},{"ForegroundId":"SpecialNode","Position":{"X":0,"Y":6}},{"ForegroundId":"SpecialNode","Position":{"X":0,"Y":7}},{"ForegroundId":"SpecialNode","Position":{"X":0,"Y":8}},{"ForegroundId":"SpecialNode","Position":{"X":0,"Y":9}},{"ForegroundId":"SpecialNode","Position":{"X":0,"Y":10}},{"ForegroundId":"SpecialNode","Position":{"X":1,"Y":10}},{"ForegroundId":"SpecialNode","Position":{"X":2,"Y":10}},{"ForegroundId":"SpecialNode","Position":{"X":3,"Y":10}},{"ForegroundId":"SpecialNode","Position":{"X":4,"Y":10}},{"ForegroundId":"SpecialNode","Position":{"X":5,"Y":10}},{"ForegroundId":"SpecialNode","Position":{"X":6,"Y":10}},{"ForegroundId":"SpecialNode","Position":{"X":7,"Y":10}},{"ForegroundId":"SpecialNode","Position":{"X":8,"Y":10}},{"ForegroundId":"SpecialNode","Position":{"X":10,"Y":1}},{"ForegroundId":"SpecialNode","Position":{"X":10,"Y":2}},{"ForegroundId":"SpecialNode","Position":{"X":10,"Y":3}},{"ForegroundId":"SpecialNode","Position":{"X":10,"Y":4}},{"ForegroundId":"SpecialNode","Position":{"X":10,"Y":5}},{"ForegroundId":"SpecialNode","Position":{"X":10,"Y":6}},{"ForegroundId":"SpecialNode","Position":{"X":10,"Y":7}},{"ForegroundId":"SpecialNode","Position":{"X":10,"Y":8}}]